meg_django_twitter_bootstrap-0.6.1.dist-info/DESCRIPTION.rst
meg_django_twitter_bootstrap-0.6.1.dist-info/METADATA
meg_django_twitter_bootstrap-0.6.1.dist-info/RECORD
meg_django_twitter_bootstrap-0.6.1.dist-info/WHEEL
meg_django_twitter_bootstrap-0.6.1.dist-info/metadata.json
meg_django_twitter_bootstrap-0.6.1.dist-info/top_level.txt
twitter_bootstrap/__init__.py
twitter_bootstrap/models.py
twitter_bootstrap/tests.py
twitter_bootstrap/views.py
twitter_bootstrap/static/css/bootstrap-responsive.css
twitter_bootstrap/static/css/bootstrap-responsive.min.css
twitter_bootstrap/static/css/bootstrap.css
twitter_bootstrap/static/css/bootstrap.min.css
twitter_bootstrap/static/js/bootstrap.js
twitter_bootstrap/static/js/bootstrap.min.js
twitter_bootstrap/templates/barebones.html
twitter_bootstrap/templates/base.html
twitter_bootstrap/templates/fluid.html
twitter_bootstrap/templates/marketing.html
