Metadata-Version: 2.0
Name: meg-django-twitter-bootstrap
Version: 0.6.1
Summary: Base bootstrap templates for django sites.
Home-page: https://git.megsupporttools.com/misc/django-twitter-bootstrap
Author: MEG Support Tools
Author-email: info@medicaleguides.com
License: LICENSE.txt
Platform: UNKNOWN
